bibcheck/__init__.py
bibcheck/bibcheck.py
bibcheck-0.1.0.dist-info/licenses/LICENSE
bibcheck-0.1.0.dist-info/METADATA
bibcheck-0.1.0.dist-info/WHEEL
bibcheck-0.1.0.dist-info/entry_points.txt
bibcheck-0.1.0.dist-info/top_level.txt
bibcheck-0.1.0.dist-info/RECORD
