Metadata-Version: 2.4
Name: bibcheck
Version: 0.1.0
Summary: A tool for checking and completing BibTeX files using DOI and arXiv entries
Author-email: Xu He <mailhexu@gmail.com>
License: MIT License
Project-URL: Homepage, https://github.com/mailhexu/bibcheck
Project-URL: Bug Tracker, https://github.com/mailhexu/bibcheck/issues
Classifier: Development Status :: 3 - Alpha
Classifier: Intended Audience :: Science/Research
Classifier: License :: OSI Approved :: MIT License
Classifier: Operating System :: OS Independent
Classifier: Programming Language :: Python :: 3
Classifier: Programming Language :: Python :: 3.7
Classifier: Programming Language :: Python :: 3.8
Classifier: Programming Language :: Python :: 3.9
Classifier: Programming Language :: Python :: 3.10
Classifier: Topic :: Scientific/Engineering
Classifier: Topic :: Text Processing :: Markup :: LaTeX
Requires-Python: >=3.7
License-File: LICENSE
Requires-Dist: bibtexparser>=1.4.0
Requires-Dist: requests>=2.25.0
Dynamic: license-file
